gcp_managed/__init__.py
gcp_managed/consumer.py
gcp_managed/producer.py
gcp_managed/utilities.py
gcp_managed-1.0.5.dist-info/METADATA
gcp_managed-1.0.5.dist-info/WHEEL
gcp_managed-1.0.5.dist-info/top_level.txt
gcp_managed-1.0.5.dist-info/RECORD
