Metadata-Version: 2.1
Name: gcp-managed
Version: 1.0.5
Summary: App to produce and consume twitter json stream data
Author-email: prabhu <prabhupad@somwwhe.com>
Classifier: Programming Language :: Python :: 3
Classifier: License :: OSI Approved :: MIT License
Classifier: Operating System :: OS Independent
Requires-Python: >=3.7
